{"GlobalPropertiesHash":"2ilJ2M8+ZdH0swl4cXFj9Ji8kay0R08ISE/fEc+OL0o=","FingerprintPatternsHash":"8ZRc1sGeVrPBx4lD717BgRaQekyh78QKV9SKsdt638U=","PropertyOverridesHash":"8ZRc1sGeVrPBx4lD717BgRaQekyh78QKV9SKsdt638U=","InputHashes":["ijrhKmc5p0kvE3348bDO3wlmv2Le/qIczJcHCUdl3Ak=","ovOMo\u002BH92/M17NNKseoW\u002B9agv4LmbLpV9TD7DZvd5ZM=","1uHP3TKnd5vQucfN5t4fyB2LcZhf2Hej3mufwzoEuXE=","agZBMKuRY\u002B5CytUUpZfgmFRUuhfRau8RD0gpximhBDY=","//TisdhXpvt2SH1xgdzYQXtO02YVzgnEY2et55oucfM=","KrCw2p5pRAWEMzUMwZUGIL7JBOQnmOBkFtgCkH8VR2k=","q1qQuQs4T3oNxXhaYbaPowHbbHPg8QpHrXLpGDz0/cE="],"CachedAssets":{"q1qQuQs4T3oNxXhaYbaPowHbbHPg8QpHrXLpGDz0/cE=":{"Identity":"F:\\Projects\\RardiV2\\Rardi\\Rardi\\obj\\Debug\\net9.0-ios\\iossimulator-x64\\compressed\\9jpflg1ys3-y9wjjswjms.gz","SourceId":"Rardi","SourceType":"Computed","ContentRoot":"F:\\Projects\\RardiV2\\Rardi\\Rardi\\obj\\Debug\\net9.0-ios\\iossimulator-x64\\compressed\\","BasePath":"/","RelativePath":"Rardi#[.{fingerprint=y9wjjswjms}]?.styles.css.gz","AssetKind":"All","AssetMode":"CurrentProject","AssetRole":"Alternative","AssetMergeBehavior":null,"AssetMergeSource":"","RelatedAsset":"F:\\Projects\\RardiV2\\Rardi\\Rardi\\obj\\Debug\\net9.0-ios\\iossimulator-x64\\scopedcss\\bundle\\Rardi.styles.css","AssetTraitName":"Content-Encoding","AssetTraitValue":"gzip","Fingerprint":"l9g8y1erdy","Integrity":"WaoA\u002B9s9IbAe/ZzRaAUCBzi2m\u002BeNidcATcLSIv\u002BqrIw=","CopyToOutputDirectory":"Never","CopyToPublishDirectory":"PreserveNewest","OriginalItemSpec":"F:\\Projects\\RardiV2\\Rardi\\Rardi\\obj\\Debug\\net9.0-ios\\iossimulator-x64\\scopedcss\\bundle\\Rardi.styles.css","FileLength":84,"LastWriteTime":"2025-11-08T13:08:50.13942+00:00"},"KrCw2p5pRAWEMzUMwZUGIL7JBOQnmOBkFtgCkH8VR2k=":{"Identity":"F:\\Projects\\RardiV2\\Rardi\\Rardi\\obj\\Debug\\net9.0-ios\\iossimulator-x64\\compressed\\fvwoso0dbg-2zs5yqkzs1.gz","SourceId":"Rardi","SourceType":"Discovered","ContentRoot":"F:\\Projects\\RardiV2\\Rardi\\Rardi\\obj\\Debug\\net9.0-ios\\iossimulator-x64\\compressed\\","BasePath":"/","RelativePath":"index#[.{fingerprint=2zs5yqkzs1}]?.html.gz","AssetKind":"All","AssetMode":"All","AssetRole":"Alternative","AssetMergeBehavior":null,"AssetMergeSource":"","RelatedAsset":"F:\\Projects\\RardiV2\\Rardi\\Rardi\\wwwroot\\index.html","AssetTraitName":"Content-Encoding","AssetTraitValue":"gzip","Fingerprint":"ik7llmzx4v","Integrity":"ktboheQ5ItBc8gJuYq8Tq2jZ5nqWcmUU0Nu/BLAhgQY=","CopyToOutputDirectory":"Never","CopyToPublishDirectory":"PreserveNewest","OriginalItemSpec":"F:\\Projects\\RardiV2\\Rardi\\Rardi\\wwwroot\\index.html","FileLength":367,"LastWriteTime":"2025-10-28T12:19:54.529695+00:00"},"//TisdhXpvt2SH1xgdzYQXtO02YVzgnEY2et55oucfM=":{"Identity":"F:\\Projects\\RardiV2\\Rardi\\Rardi\\obj\\Debug\\net9.0-ios\\iossimulator-x64\\compressed\\rhy1137ubm-obgb1x923p.gz","SourceId":"Rardi","SourceType":"Discovered","ContentRoot":"F:\\Projects\\RardiV2\\Rardi\\Rardi\\obj\\Debug\\net9.0-ios\\iossimulator-x64\\compressed\\","BasePath":"/","RelativePath":"app#[.{fingerprint=obgb1x923p}]?.css.gz","AssetKind":"All","AssetMode":"All","AssetRole":"Alternative","AssetMergeBehavior":null,"AssetMergeSource":"","RelatedAsset":"F:\\Projects\\RardiV2\\Rardi\\Rardi\\wwwroot\\app.css","AssetTraitName":"Content-Encoding","AssetTraitValue":"gzip","Fingerprint":"5zhondbskl","Integrity":"Aexltm0A6MBrFI1/TfKNHYfDf6t4vPbd8tG9GeAeifs=","CopyToOutputDirectory":"Never","CopyToPublishDirectory":"PreserveNewest","OriginalItemSpec":"F:\\Projects\\RardiV2\\Rardi\\Rardi\\wwwroot\\app.css","FileLength":236,"LastWriteTime":"2025-10-28T12:19:54.529695+00:00"},"agZBMKuRY\u002B5CytUUpZfgmFRUuhfRau8RD0gpximhBDY=":{"Identity":"F:\\Projects\\RardiV2\\Rardi\\Rardi\\obj\\Debug\\net9.0-ios\\iossimulator-x64\\compressed\\xa5fgxnhtc-g1x2ayen6w.gz","SourceId":"CodeBeam.MudBlazor.Extensions","SourceType":"Package","ContentRoot":"F:\\Projects\\RardiV2\\Rardi\\Rardi\\obj\\Debug\\net9.0-ios\\iossimulator-x64\\compressed\\","BasePath":"_content/CodeBeam.MudBlazor.Extensions","RelativePath":"MudExtensions.min.js.gz","AssetKind":"All","AssetMode":"All","AssetRole":"Alternative","AssetMergeBehavior":null,"AssetMergeSource":"","RelatedAsset":"C:\\Users\\User\\.nuget\\packages\\codebeam.mudblazor.extensions\\8.2.4\\staticwebassets\\MudExtensions.min.js","AssetTraitName":"Content-Encoding","AssetTraitValue":"gzip","Fingerprint":"ew72rf4g2a","Integrity":"fmtfxHW2ZasLSq\u002BVgaVZEc\u002BgDVqgGJJv3OT5mNbWYLY=","CopyToOutputDirectory":"Never","CopyToPublishDirectory":"PreserveNewest","OriginalItemSpec":"C:\\Users\\User\\.nuget\\packages\\codebeam.mudblazor.extensions\\8.2.4\\staticwebassets\\MudExtensions.min.js","FileLength":1772,"LastWriteTime":"2025-10-28T12:19:54.5289419+00:00"},"1uHP3TKnd5vQucfN5t4fyB2LcZhf2Hej3mufwzoEuXE=":{"Identity":"F:\\Projects\\RardiV2\\Rardi\\Rardi\\obj\\Debug\\net9.0-ios\\iossimulator-x64\\compressed\\y71s3w5f9p-zrxbvx041h.gz","SourceId":"CodeBeam.MudBlazor.Extensions","SourceType":"Package","ContentRoot":"F:\\Projects\\RardiV2\\Rardi\\Rardi\\obj\\Debug\\net9.0-ios\\iossimulator-x64\\compressed\\","BasePath":"_content/CodeBeam.MudBlazor.Extensions","RelativePath":"MudExtensions.min.css.gz","AssetKind":"All","AssetMode":"All","AssetRole":"Alternative","AssetMergeBehavior":null,"AssetMergeSource":"","RelatedAsset":"C:\\Users\\User\\.nuget\\packages\\codebeam.mudblazor.extensions\\8.2.4\\staticwebassets\\MudExtensions.min.css","AssetTraitName":"Content-Encoding","AssetTraitValue":"gzip","Fingerprint":"jr5dk663oe","Integrity":"b\u002BrutkeTgH1ArwTha/G6hVZuk06vhFHxKr3WlLSSbbE=","CopyToOutputDirectory":"Never","CopyToPublishDirectory":"PreserveNewest","OriginalItemSpec":"C:\\Users\\User\\.nuget\\packages\\codebeam.mudblazor.extensions\\8.2.4\\staticwebassets\\MudExtensions.min.css","FileLength":4315,"LastWriteTime":"2025-10-28T12:19:54.529695+00:00"},"ovOMo\u002BH92/M17NNKseoW\u002B9agv4LmbLpV9TD7DZvd5ZM=":{"Identity":"F:\\Projects\\RardiV2\\Rardi\\Rardi\\obj\\Debug\\net9.0-ios\\iossimulator-x64\\compressed\\0wz98yz2xy-tjzqk7tnel.gz","SourceId":"MudBlazor","SourceType":"Package","ContentRoot":"F:\\Projects\\RardiV2\\Rardi\\Rardi\\obj\\Debug\\net9.0-ios\\iossimulator-x64\\compressed\\","BasePath":"_content/MudBlazor","RelativePath":"MudBlazor.min.js.gz","AssetKind":"All","AssetMode":"All","AssetRole":"Alternative","AssetMergeBehavior":null,"AssetMergeSource":"","RelatedAsset":"C:\\Users\\User\\.nuget\\packages\\mudblazor\\8.13.0\\staticwebassets\\MudBlazor.min.js","AssetTraitName":"Content-Encoding","AssetTraitValue":"gzip","Fingerprint":"suz25w9iin","Integrity":"/ChD1T0FUN3t0/HkZ\u002BmFgcq0Q\u002BkqigyGPgUdxTYdxAQ=","CopyToOutputDirectory":"Never","CopyToPublishDirectory":"PreserveNewest","OriginalItemSpec":"C:\\Users\\User\\.nuget\\packages\\mudblazor\\8.13.0\\staticwebassets\\MudBlazor.min.js","FileLength":16435,"LastWriteTime":"2025-10-28T12:19:54.5307042+00:00"},"ijrhKmc5p0kvE3348bDO3wlmv2Le/qIczJcHCUdl3Ak=":{"Identity":"F:\\Projects\\RardiV2\\Rardi\\Rardi\\obj\\Debug\\net9.0-ios\\iossimulator-x64\\compressed\\tzxjg6is5z-jk5eo7zo4m.gz","SourceId":"MudBlazor","SourceType":"Package","ContentRoot":"F:\\Projects\\RardiV2\\Rardi\\Rardi\\obj\\Debug\\net9.0-ios\\iossimulator-x64\\compressed\\","BasePath":"_content/MudBlazor","RelativePath":"MudBlazor.min.css.gz","AssetKind":"All","AssetMode":"All","AssetRole":"Alternative","AssetMergeBehavior":null,"AssetMergeSource":"","RelatedAsset":"C:\\Users\\User\\.nuget\\packages\\mudblazor\\8.13.0\\staticwebassets\\MudBlazor.min.css","AssetTraitName":"Content-Encoding","AssetTraitValue":"gzip","Fingerprint":"jhl93wd8k2","Integrity":"\u002BfdV\u002BWnGrTzpKqpfujPjqVLyUVt000cHgXKK3yBlEtU=","CopyToOutputDirectory":"Never","CopyToPublishDirectory":"PreserveNewest","OriginalItemSpec":"C:\\Users\\User\\.nuget\\packages\\mudblazor\\8.13.0\\staticwebassets\\MudBlazor.min.css","FileLength":65131,"LastWriteTime":"2025-10-28T12:19:54.5360404+00:00"}},"CachedCopyCandidates":{}}